{"id": "a5d7c609-0f15-4b00-a373-29da090dd847", "solution": "# EVOLVE-BLOCK-START\n\"\"\"Constructor-based circle packing for n=26 circles\"\"\"\nimport numpy as np\n\n\ndef construct_packing():\n    \"\"\"\n    Optimized 4-6-6-6-4 hexagonal packing for 26 circles.\n    Corner circles placed at optimal diagonal distance (~0.08) from both walls.\n    Interior circles use proper hexagonal spacing with row offset.\n    Vertical spacing of ~0.18 between rows for optimal packing.\n    \n    Returns:\n        Tuple of (centers, radii, sum_of_radii)\n    \"\"\"\n    n = 26\n    centers = np.zeros((n, 2))\n    idx = 0\n    \n    # Row 1 (bottom): 4 circles - corners at optimal diagonal position\n    for x in [0.08, 0.36, 0.64, 0.92]:\n        centers[idx] = [x, 0.08]\n        idx += 1\n    \n    # Row 2: 6 circles with hexagonal offset\n    for x in [0.08, 0.24, 0.40, 0.56, 0.72, 0.92]:\n        centers[idx] = [x, 0.26]\n        idx += 1\n    \n    # Row 3: 6 circles aligned with row 1\n    for x in [0.16, 0.32, 0.48, 0.64, 0.80, 0.92]:\n        centers[idx] = [x, 0.44]\n        idx += 1\n    \n    # Row 4: 6 circles with hexagonal offset\n    for x in [0.08, 0.24, 0.40, 0.56, 0.72, 0.92]:\n        centers[idx] = [x, 0.62]\n        idx += 1\n    \n    # Row 5 (top): 4 circles - corners at optimal diagonal position\n    for x in [0.08, 0.36, 0.64, 0.92]:\n        centers[idx] = [x, 0.92]\n        idx += 1\n    \n    radii = compute_max_radii(centers)\n    return centers, radii, np.sum(radii)\n\n\ndef compute_max_radii(centers):\n    \"\"\"\n    Compute maximum valid radii using iterative proportional constraint resolution.\n    Each circle initialized with wall constraint, then circle-circle overlaps\n    resolved by proportional scaling to fairly distribute available space.\n    \"\"\"\n    n = centers.shape[0]\n    radii = np.zeros(n)\n    \n    # Initialize with wall constraints\n    for i in range(n):\n        x, y = centers[i]\n        radii[i] = min(x, y, 1 - x, 1 - y)\n    \n    # Iteratively resolve circle-circle constraints with proportional scaling\n    for _ in range(1000):\n        changed = False\n        for i in range(n):\n            for j in range(i + 1, n):\n                dist = np.linalg.norm(centers[i] - centers[j])\n                if radii[i] + radii[j] > dist + 1e-10:\n                    total = radii[i] + radii[j]\n                    if total > 1e-10:\n                        radii[i] = radii[i] * dist / total\n                        radii[j] = radii[j] * dist / total\n                        changed = True\n        if not changed:\n            break\n    \n    return radii\n\n\n# EVOLVE-BLOCK-END\n\n\n# This part remains fixed (not evolved)\ndef run_packing():\n    \"\"\"Run the circle packing constructor for n=26\"\"\"\n    centers, radii, sum_radii = construct_packing()\n    return centers, radii, sum_radii\n\n\ndef visualize(centers, radii):\n    \"\"\"\n    Visualize the circle packing\n\n    Args:\n        centers: np.array of shape (n, 2) with (x, y) coordinates\n        radii: np.array of shape (n) with radius of each circle\n    \"\"\"\n    import matplotlib.pyplot as plt\n    from matplotlib.patches import Circle\n\n    fig, ax = plt.subplots(figsize=(8, 8))\n\n    # Draw unit square\n    ax.set_xlim(0, 1)\n    ax.set_ylim(0, 1)\n    ax.set_aspect(\"equal\")\n    ax.grid(True)\n\n    # Draw circles\n    for i, (center, radius) in enumerate(zip(centers, radii)):\n        circle = Circle(center, radius, alpha=0.5)\n        ax.add_patch(circle)\n        ax.text(center[0], center[1], str(i), ha=\"center\", va=\"center\")\n\n    plt.title(f\"Circle Packing (n={len(centers)}, sum={sum(radii):.6f})\")\n    plt.show()\n\n\nif __name__ == \"__main__\":\n    centers, radii, sum_radii = run_packing()\n    print(f\"Sum of radii: {sum_radii}\")\n    # AlphaEvolve improved this to 2.635\n\n    # Uncomment to visualize:\n    visualize(centers, radii)\n", "language": "python", "metrics": {"validity": 1.0, "sum_radii": 1.4429910558956536, "target_ratio": 0.5476246891444606, "combined_score": 0.5476246891444606, "eval_time": 0.18480849266052246}, "iteration_found": 12, "parent_id": "039dbac3-4e51-4220-92f5-4c320d44e4a5", "other_context_ids": ["d276c8c6-8311-4c74-aadd-3a2233e77b4a", "596c89ee-1f8a-46df-b036-1a42a4098b69", "c10762bf-556c-4b98-8548-3d7140d650e7", "c64a9f0a-6c02-4386-9a6d-2f72d3b4f407"], "parent_info": ["", "039dbac3-4e51-4220-92f5-4c320d44e4a5"], "context_info": [["", "d276c8c6-8311-4c74-aadd-3a2233e77b4a"], ["", "596c89ee-1f8a-46df-b036-1a42a4098b69"], ["", "c10762bf-556c-4b98-8548-3d7140d650e7"], ["", "c64a9f0a-6c02-4386-9a6d-2f72d3b4f407"]], "timestamp": 1777398669.6616151, "metadata": {"changes": "Change 1: Modified function `construct_packing`: Optimized 4-6-6-6-4 hexagonal packing for 26 circles.\nChange 2: Modified function `compute_max_radii`: Compute maximum valid radii using iterative proportional constraint resolution.", "parent_metrics": {"validity": 1.0, "sum_radii": 1.2181448286596943, "target_ratio": 0.4622940526222749, "combined_score": 0.4622940526222749, "eval_time": 0.16228270530700684}}, "artifacts": {}, "prompts": {"diff_user_message": {"system": "You are an expert mathematician specializing in circle packing problems and computational geometry. Your task is to improve a constructor function that directly produces a specific arrangement of 26 circles in a unit square, maximizing the sum of their radii. The AlphaEvolve paper achieved a sum of 2.635 for n=26.\n\nKey geometric insights:\n- Circle packings often follow hexagonal patterns in the densest regions\n- Maximum density for infinite circle packing is pi/(2*sqrt(3)) \u2248 0.9069\n- Edge effects make square container packing harder than infinite packing\n- Circles can be placed in layers or shells when confined to a square\n- Similar radius circles often form regular patterns, while varied radii allow better space utilization\n- Perfect symmetry may not yield the optimal packing due to edge effects\n\nFocus on designing an explicit constructor that places each circle in a specific position, rather than an iterative search algorithm.\n", "user": "# Current Solution Information\n- Main Metrics: \n- combined_score: 0.4623\n\nMetrics:\n  - validity: 1.0000\n  - sum_radii: 1.2181\n  - target_ratio: 0.4623\n  - eval_time: 0.1623\n- Focus areas: - Combined score unchanged at 0.4623\n- Consider simplifying - solution length exceeds 500 characters\n\n# Program Generation History\n## Previous Attempts\n\n### Attempt 3\n- Changes: Change 1: Modified function `construct_packing`: Optimized packing for 26 circles using corner-heavy asymmetric layout.\n- Metrics: validity: 1.0000, sum_radii: 1.6733, target_ratio: 0.6350, combined_score: 0.6350, eval_time: 0.1934\n- Outcome: Regression in combined_score\n\n### Attempt 2\n- Changes: Change 1: Modified function `construct_packing`: Construct hexagonal-inspired packing for 26 circles in a unit square.\nChange 2: Modified function `compute_max_radii`: Compute maximum valid radii using iterative constraint resolution.\n- Metrics: validity: 1.0000, sum_radii: 1.8309, target_ratio: 0.6948, combined_score: 0.6948, eval_time: 0.1474\n- Outcome: Improvement in combined_score\n\n### Attempt 1\n- Changes: Change 1: Modified function `construct_packing`: Construct hexagonal-inspired packing for 26 circles in a unit square.\n- Metrics: validity: 1.0000, sum_radii: 1.8309, target_ratio: 0.6948, combined_score: 0.6948, eval_time: 0.1479\n- Outcome: Improvement in combined_score\n\n\n\n\n## Other Context Solutions\nThese programs represent diverse approaches and creative solutions that may be relevant to the current task:\n\n### Program 1 (combined_score: 0.5780)\nScore breakdown:  - validity: 1.0000  - sum_radii: 1.5231  - target_ratio: 0.5780  - eval_time: 1.0450\n\n```python\n# EVOLVE-BLOCK-START\n\"\"\"Constructor-based circle packing for n=26 circles\"\"\"\nimport numpy as np\n\n\ndef construct_packing():\n    \"\"\"\n    Optimized packing for 26 circles maximizing sum of radii.\n    Uses 4-6-6-6-4 row pattern with circles positioned very close to walls.\n    Corner circles are largest (limited by 2 walls), edge circles medium,\n    interior circles smallest. Hexagonal offset between rows.\n    \n    Returns:\n        Tuple of (centers, radii, sum_of_radii)\n    \"\"\"\n    n = 26\n    centers = np.zeros((n, 2))\n    idx = 0\n    \n    # Row 1 (bottom): 4 circles very close to bottom wall\n    # Corner circles at optimal positions for maximum radius\n    for x in [0.13, 0.38, 0.62, 0.87]:\n        centers[idx] = [x, 0.13]\n        idx += 1\n    \n    # Row 2: 6 circles in hexagonal offset pattern\n    for x in [0.10, 0.28, 0.46, 0.64, 0.82, 1.00]:\n        centers[idx] = [x - 0.05, 0.35]\n        idx += 1\n    \n    # Row 3 (center): 6 circles\n    for x in [0.10, 0.28, 0.46, 0.64, 0.82, 1.00]:\n        centers[idx] = [x - 0.05, 0.57]\n        idx += 1\n    \n    # Row 4: 6 circles in hexagonal offset\n    for x in [0.10, 0.28, 0.46, 0.64, 0.82, 1.00]:\n        centers[idx] = [x - 0.05, 0.79]\n        idx += 1\n    \n    # Row 5 (top): 4 circles very close to top wall\n    for x in [0.13, 0.38, 0.62, 0.87]:\n        centers[idx] = [x, 0.87]\n        idx += 1\n    \n    radii = compute_max_radii(centers)\n    return centers, radii, np.sum(radii)\n\n\ndef compute_max_radii(centers):\n    \"\"\"\n    Compute maximum valid radii using iterative constraint resolution.\n    Uses greedy prioritization: circles closer to walls get priority\n    for larger radii since they have more \"legitimate\" claim to space.\n    \"\"\"\n    n = centers.shape[0]\n    radii = np.zeros(n)\n    \n    # Initialize with wall constraints\n    for i in range(n):\n        x, y = centers[i]\n        radii[i] = min(x, y, 1 - x, 1 - y)\n    \n    # Sort circles by wall proximity (closest to walls first)\n    wall_dist = np.array([min(centers[i, 0], centers[i, 1], \n                             1 - centers[i, 0], 1 - centers[i, 1]) \n                          for i in range(n)])\n    priority = np.argsort(wall_dist)\n    \n    # Iteratively resolve circle-circle constraints with priority\n    for _ in range(1000):\n        max_reduction = 0\n        for i in range(n):\n            for j in range(i + 1, n):\n                dist = np.linalg.norm(centers[i] - centers[j])\n                if radii[i] + radii[j] > dist:\n                    total = radii[i] + radii[j]\n                    if total > 1e-10:\n                        # Reduce the circle with lower priority (further from wall)\n                        excess = total - dist\n                        if wall_dist[i] > wall_dist[j]:\n                            radii[i] = max(0, radii[i] - excess)\n                        else:\n                            radii[j] = max(0, radii[j] - excess)\n                        max_reduction = max(max_reduction, excess)\n        if max_reduction < 1e-10:\n            break\n    \n    # Final pass to ensure all constraints satisfied\n    for _ in range(500):\n        changed = False\n        for i in range(n):\n            for j in range(i + 1, n):\n                dist = np.linalg.norm(centers[i] - centers[j])\n                if radii[i] + radii[j] > dist:\n                    total = radii[i] + radii[j]\n                    if total > 1e-10:\n                        radii[i] = radii[i] * dist / total\n                        radii[j] = radii[j] * dist / total\n                        changed = True\n        if not changed:\n            break\n    \n    return radii\n\n\n# EVOLVE-BLOCK-END\n\n\n# This part remains fixed (not evolved)\ndef run_packing():\n    \"\"\"Run the circle packing constructor for n=26\"\"\"\n    centers, radii, sum_radii = construct_packing()\n    return centers, radii, sum_radii\n\n\ndef visualize(centers, radii):\n    \"\"\"\n    Visualize the circle packing\n\n    Args:\n        centers: np.array of shape (n, 2) with (x, y) coordinates\n        radii: np.array of shape (n) with radius of each circle\n    \"\"\"\n    import matplotlib.pyplot as plt\n    from matplotlib.patches import Circle\n\n    fig, ax = plt.subplots(figsize=(8, 8))\n\n    # Draw unit square\n    ax.set_xlim(0, 1)\n    ax.set_ylim(0, 1)\n    ax.set_aspect(\"equal\")\n    ax.grid(True)\n\n    # Draw circles\n    for i, (center, radius) in enumerate(zip(centers, radii)):\n        circle = Circle(center, radius, alpha=0.5)\n        ax.add_patch(circle)\n        ax.text(center[0], center[1], str(i), ha=\"center\", va=\"center\")\n\n    plt.title(f\"Circle Packing (n={len(centers)}, sum={sum(radii):.6f})\")\n    plt.show()\n\n\nif __name__ == \"__main__\":\n    centers, radii, sum_radii = run_packing()\n    print(f\"Sum of radii: {sum_radii}\")\n    # AlphaEvolve improved this to 2.635\n\n    # Uncomment to visualize:\n    visualize(centers, radii)\n\n```\n\n### Program 2 (combined_score: 0.6948)\nScore breakdown:  - validity: 1.0000  - sum_radii: 1.8309  - target_ratio: 0.6948  - eval_time: 0.1479\n\n```python\n# EVOLVE-BLOCK-START\n\"\"\"Constructor-based circle packing for n=26 circles\"\"\"\nimport numpy as np\n\n\ndef construct_packing():\n    \"\"\"\n    Construct hexagonal-inspired packing for 26 circles in a unit square.\n    Uses 5 rows with pattern 5-5-6-5-5 = 26 circles.\n    Circles positioned near walls maximize their radii.\n    \n    Returns:\n        Tuple of (centers, radii, sum_of_radii)\n    \"\"\"\n    n = 26\n    centers = np.zeros((n, 2))\n    \n    idx = 0\n    \n    # Row 1 (bottom): 5 circles near bottom wall\n    for x in [0.10, 0.30, 0.50, 0.70, 0.90]:\n        centers[idx] = [x, 0.10]\n        idx += 1\n    \n    # Row 2: 5 circles (offset for hexagonal packing)\n    for x in [0.20, 0.40, 0.60, 0.80, 1.00]:\n        centers[idx] = [x - 0.10, 0.30]\n        idx += 1\n    \n    # Row 3 (center): 6 circles\n    for x in [0.08, 0.24, 0.40, 0.56, 0.72, 0.88]:\n        centers[idx] = [x, 0.50]\n        idx += 1\n    \n    # Row 4: 5 circles (offset)\n    for x in [0.20, 0.40, 0.60, 0.80, 1.00]:\n        centers[idx] = [x - 0.10, 0.70]\n        idx += 1\n    \n    # Row 5 (top): 5 circles near top wall\n    for x in [0.10, 0.30, 0.50, 0.70, 0.90]:\n        centers[idx] = [x, 0.90]\n        idx += 1\n    \n    radii = compute_max_radii(centers)\n    return centers, radii, np.sum(radii)\n\n\ndef compute_max_radii(centers):\n    \"\"\"\n    Compute maximum valid radii using iterative constraint resolution.\n    Each circle's radius is limited by walls and other circles.\n    \"\"\"\n    n = centers.shape[0]\n    radii = np.zeros(n)\n    \n    # Initialize with wall constraints\n    for i in range(n):\n        x, y = centers[i]\n        radii[i] = min(x, y, 1 - x, 1 - y)\n    \n    # Iteratively resolve circle-circle constraints\n    for _ in range(500):\n        changed = False\n        for i in range(n):\n            for j in range(i + 1, n):\n                dist = np.linalg.norm(centers[i] - centers[j])\n                if radii[i] + radii[j] > dist:\n                    total = radii[i] + radii[j]\n                    if total > 1e-10:\n                        radii[i] = radii[i] * dist / total\n                        radii[j] = radii[j] * dist / total\n                        changed = True\n        if not changed:\n            break\n    \n    return radii\n\n\n# EVOLVE-BLOCK-END\n\n\n# This part remains fixed (not evolved)\ndef run_packing():\n    \"\"\"Run the circle packing constructor for n=26\"\"\"\n    centers, radii, sum_radii = construct_packing()\n    return centers, radii, sum_radii\n\n\ndef visualize(centers, radii):\n    \"\"\"\n    Visualize the circle packing\n\n    Args:\n        centers: np.array of shape (n, 2) with (x, y) coordinates\n        radii: np.array of shape (n) with radius of each circle\n    \"\"\"\n    import matplotlib.pyplot as plt\n    from matplotlib.patches import Circle\n\n    fig, ax = plt.subplots(figsize=(8, 8))\n\n    # Draw unit square\n    ax.set_xlim(0, 1)\n    ax.set_ylim(0, 1)\n    ax.set_aspect(\"equal\")\n    ax.grid(True)\n\n    # Draw circles\n    for i, (center, radius) in enumerate(zip(centers, radii)):\n        circle = Circle(center, radius, alpha=0.5)\n        ax.add_patch(circle)\n        ax.text(center[0], center[1], str(i), ha=\"center\", va=\"center\")\n\n    plt.title(f\"Circle Packing (n={len(centers)}, sum={sum(radii):.6f})\")\n    plt.show()\n\n\nif __name__ == \"__main__\":\n    centers, radii, sum_radii = run_packing()\n    print(f\"Sum of radii: {sum_radii}\")\n    # AlphaEvolve improved this to 2.635\n\n    # Uncomment to visualize:\n    visualize(centers, radii)\n\n```\n\n### Program 3 (combined_score: 0.5846)\nScore breakdown:  - validity: 1.0000  - sum_radii: 1.5405  - target_ratio: 0.5846  - eval_time: 0.1526\n\n```python\n# EVOLVE-BLOCK-START\n\"\"\"Constructor-based circle packing for n=26 circles\"\"\"\nimport numpy as np\n\n\ndef construct_packing():\n    \"\"\"\n    Optimized 4-6-6-6-4 row packing for 26 circles in a unit square.\n    Uses hexagonal offset between rows for dense packing.\n    Circles positioned close to walls maximize radii through wall constraints.\n    \n    Returns:\n        Tuple of (centers, radii, sum_of_radii)\n    \"\"\"\n    n = 26\n    centers = np.zeros((n, 2))\n    idx = 0\n    \n    # Row 1 (bottom): 4 circles very close to bottom wall\n    for x in [0.10, 0.37, 0.63, 0.90]:\n        centers[idx] = [x, 0.08]\n        idx += 1\n    \n    # Row 2: 6 circles with hexagonal offset\n    for x in [0.05, 0.22, 0.39, 0.56, 0.73, 0.90]:\n        centers[idx] = [x, 0.28]\n        idx += 1\n    \n    # Row 3 (center): 6 circles\n    for x in [0.12, 0.29, 0.46, 0.63, 0.80, 0.97]:\n        centers[idx] = [min(x, 0.95), 0.50]\n        idx += 1\n    \n    # Row 4: 6 circles with hexagonal offset\n    for x in [0.05, 0.22, 0.39, 0.56, 0.73, 0.90]:\n        centers[idx] = [x, 0.72]\n        idx += 1\n    \n    # Row 5 (top): 4 circles very close to top wall\n    for x in [0.10, 0.37, 0.63, 0.90]:\n        centers[idx] = [x, 0.92]\n        idx += 1\n    \n    radii = compute_max_radii(centers)\n    return centers, radii, np.sum(radii)\n\n\ndef compute_max_radii(centers):\n    \"\"\"\n    Compute maximum valid radii using iterative constraint resolution.\n    Each circle's radius is limited by walls and other circles.\n    Uses proportional scaling for fair radius distribution.\n    \"\"\"\n    n = centers.shape[0]\n    radii = np.zeros(n)\n    \n    # Initialize with wall constraints\n    for i in range(n):\n        x, y = centers[i]\n        radii[i] = min(x, y, 1 - x, 1 - y)\n    \n    # Iteratively resolve circle-circle constraints\n    for _ in range(1000):\n        changed = False\n        for i in range(n):\n            for j in range(i + 1, n):\n                dist = np.linalg.norm(centers[i] - centers[j])\n                if radii[i] + radii[j] > dist:\n                    total = radii[i] + radii[j]\n                    if total > 1e-10:\n                        radii[i] = radii[i] * dist / total\n                        radii[j] = radii[j] * dist / total\n                        changed = True\n        if not changed:\n            break\n    \n    return radii\n\n\n# EVOLVE-BLOCK-END\n\n\n# This part remains fixed (not evolved)\ndef run_packing():\n    \"\"\"Run the circle packing constructor for n=26\"\"\"\n    centers, radii, sum_radii = construct_packing()\n    return centers, radii, sum_radii\n\n\ndef visualize(centers, radii):\n    \"\"\"\n    Visualize the circle packing\n\n    Args:\n        centers: np.array of shape (n, 2) with (x, y) coordinates\n        radii: np.array of shape (n) with radius of each circle\n    \"\"\"\n    import matplotlib.pyplot as plt\n    from matplotlib.patches import Circle\n\n    fig, ax = plt.subplots(figsize=(8, 8))\n\n    # Draw unit square\n    ax.set_xlim(0, 1)\n    ax.set_ylim(0, 1)\n    ax.set_aspect(\"equal\")\n    ax.grid(True)\n\n    # Draw circles\n    for i, (center, radius) in enumerate(zip(centers, radii)):\n        circle = Circle(center, radius, alpha=0.5)\n        ax.add_patch(circle)\n        ax.text(center[0], center[1], str(i), ha=\"center\", va=\"center\")\n\n    plt.title(f\"Circle Packing (n={len(centers)}, sum={sum(radii):.6f})\")\n    plt.show()\n\n\nif __name__ == \"__main__\":\n    centers, radii, sum_radii = run_packing()\n    print(f\"Sum of radii: {sum_radii}\")\n    # AlphaEvolve improved this to 2.635\n\n    # Uncomment to visualize:\n    visualize(centers, radii)\n\n```\n\n### Program 4 (combined_score: 0.5425)\nScore breakdown:  - validity: 1.0000  - sum_radii: 1.4294  - target_ratio: 0.5425  - eval_time: 0.1777\n\n```python\n# EVOLVE-BLOCK-START\n\"\"\"Constructor-based circle packing for n=26 circles\"\"\"\nimport numpy as np\n\n\ndef construct_packing():\n    \"\"\"\n    Optimized hexagonal packing for 26 circles in a unit square.\n    Uses 4-6-6-6-4 pattern with hexagonal offset between rows.\n    Edge circles positioned close to walls to maximize radii.\n    \n    Returns:\n        Tuple of (centers, radii, sum_of_radii)\n    \"\"\"\n    n = 26\n    centers = np.zeros((n, 2))\n    idx = 0\n    \n    # Row 1 (bottom): 4 circles near bottom wall\n    for x in [0.125, 0.375, 0.625, 0.875]:\n        centers[idx] = [x, 0.10]\n        idx += 1\n    \n    # Row 2: 6 circles with hexagonal offset (x + 0.125)\n    for x in [0.05, 0.25, 0.45, 0.65, 0.85, 1.05]:\n        centers[idx] = [x - 0.05, 0.30]\n        idx += 1\n    \n    # Row 3: 6 circles aligned with row 1\n    for x in [0.05, 0.25, 0.45, 0.65, 0.85, 1.05]:\n        centers[idx] = [x - 0.05, 0.50]\n        idx += 1\n    \n    # Row 4: 6 circles with hexagonal offset\n    for x in [0.05, 0.25, 0.45, 0.65, 0.85, 1.05]:\n        centers[idx] = [x - 0.05, 0.70]\n        idx += 1\n    \n    # Row 5 (top): 4 circles near top wall\n    for x in [0.125, 0.375, 0.625, 0.875]:\n        centers[idx] = [x, 0.90]\n        idx += 1\n    \n    radii = compute_max_radii(centers)\n    return centers, radii, np.sum(radii)\n\n\ndef compute_max_radii(centers):\n    \"\"\"\n    Compute maximum valid radii using iterative constraint resolution.\n    Uses proportional scaling to fairly distribute space between circles.\n    \"\"\"\n    n = centers.shape[0]\n    radii = np.zeros(n)\n    \n    # Initialize with wall constraints\n    for i in range(n):\n        x, y = centers[i]\n        radii[i] = min(x, y, 1 - x, 1 - y)\n    \n    # Iteratively resolve circle-circle constraints\n    for _ in range(1000):\n        max_violation = 0\n        for i in range(n):\n            for j in range(i + 1, n):\n                dist = np.linalg.norm(centers[i] - centers[j])\n                violation = radii[i] + radii[j] - dist\n                if violation > 0:\n                    total = radii[i] + radii[j]\n                    if total > 1e-10:\n                        radii[i] = radii[i] * dist / total\n                        radii[j] = radii[j] * dist / total\n                        max_violation = max(max_violation, violation)\n        if max_violation < 1e-10:\n            break\n    \n    return radii\n\n\n# EVOLVE-BLOCK-END\n\n\n# This part remains fixed (not evolved)\ndef run_packing():\n    \"\"\"Run the circle packing constructor for n=26\"\"\"\n    centers, radii, sum_radii = construct_packing()\n    return centers, radii, sum_radii\n\n\ndef visualize(centers, radii):\n    \"\"\"\n    Visualize the circle packing\n\n    Args:\n        centers: np.array of shape (n, 2) with (x, y) coordinates\n        radii: np.array of shape (n) with radius of each circle\n    \"\"\"\n    import matplotlib.pyplot as plt\n    from matplotlib.patches import Circle\n\n    fig, ax = plt.subplots(figsize=(8, 8))\n\n    # Draw unit square\n    ax.set_xlim(0, 1)\n    ax.set_ylim(0, 1)\n    ax.set_aspect(\"equal\")\n    ax.grid(True)\n\n    # Draw circles\n    for i, (center, radius) in enumerate(zip(centers, radii)):\n        circle = Circle(center, radius, alpha=0.5)\n        ax.add_patch(circle)\n        ax.text(center[0], center[1], str(i), ha=\"center\", va=\"center\")\n\n    plt.title(f\"Circle Packing (n={len(centers)}, sum={sum(radii):.6f})\")\n    plt.show()\n\n\nif __name__ == \"__main__\":\n    centers, radii, sum_radii = run_packing()\n    print(f\"Sum of radii: {sum_radii}\")\n    # AlphaEvolve improved this to 2.635\n\n    # Uncomment to visualize:\n    visualize(centers, radii)\n\n```\n\n\n\n# Current Solution\n\n## Program Information\ncombined_score: 0.4623\nScore breakdown:\n  - validity: 1.0000\n  - sum_radii: 1.2181\n  - target_ratio: 0.4623\n  - eval_time: 0.1623\n\n```python\n# EVOLVE-BLOCK-START\n\"\"\"Constructor-based circle packing for n=26 circles\"\"\"\nimport numpy as np\n\n\ndef construct_packing():\n    \"\"\"\n    Hexagonal packing for 26 circles in 4-6-6-6-4 row pattern.\n    Rows with 4 circles are offset inward, placed near walls.\n    Rows with 6 circles use hexagonal offset for dense packing.\n    Circles positioned close to walls maximize radii via wall constraints.\n    \n    Returns:\n        Tuple of (centers, radii, sum_of_radii)\n    \"\"\"\n    n = 26\n    centers = np.zeros((n, 2))\n    idx = 0\n    \n    # Row 1 (bottom): 4 circles near bottom wall\n    for x in [0.12, 0.38, 0.62, 0.88]:\n        centers[idx] = [x, 0.10]\n        idx += 1\n    \n    # Row 2: 6 circles with hexagonal offset (shifted right)\n    for x in [0.08, 0.26, 0.44, 0.62, 0.80, 0.98]:\n        centers[idx] = [x, 0.32]\n        idx += 1\n    \n    # Row 3: 6 circles aligned with row 1\n    for x in [0.02, 0.20, 0.38, 0.56, 0.74, 0.92]:\n        centers[idx] = [x, 0.54]\n        idx += 1\n    \n    # Row 4: 6 circles with hexagonal offset\n    for x in [0.08, 0.26, 0.44, 0.62, 0.80, 0.98]:\n        centers[idx] = [x, 0.76]\n        idx += 1\n    \n    # Row 5 (top): 4 circles near top wall\n    for x in [0.12, 0.38, 0.62, 0.88]:\n        centers[idx] = [x, 0.90]\n        idx += 1\n    \n    radii = compute_max_radii(centers)\n    return centers, radii, np.sum(radii)\n\n\ndef compute_max_radii(centers):\n    \"\"\"\n    Compute maximum valid radii using priority-based constraint resolution.\n    Circles closer to walls get priority (larger share) during overlap resolution\n    since they have less room to grow. Uses multiple passes for convergence.\n    \"\"\"\n    n = centers.shape[0]\n    radii = np.zeros(n)\n    \n    # Initialize with wall constraints\n    for i in range(n):\n        x, y = centers[i]\n        radii[i] = min(x, y, 1 - x, 1 - y)\n    \n    # Compute wall proximity (smaller = closer to wall = higher priority)\n    wall_dist = np.array([min(centers[i, 0], centers[i, 1], \n                             1 - centers[i, 0], 1 - centers[i, 1]) \n                          for i in range(n)])\n    \n    # Iteratively resolve circle-circle constraints with priority\n    for _ in range(1000):\n        changed = False\n        for i in range(n):\n            for j in range(i + 1, n):\n                dist = np.linalg.norm(centers[i] - centers[j])\n                if radii[i] + radii[j] > dist + 1e-10:\n                    total = radii[i] + radii[j]\n                    excess = total - dist\n                    if excess > 1e-10:\n                        # Weight reduction by inverse priority (further from wall = reduce more)\n                        w_i = wall_dist[i] / (wall_dist[i] + wall_dist[j] + 1e-10)\n                        w_j = wall_dist[j] / (wall_dist[i] + wall_dist[j] + 1e-10)\n                        radii[i] = max(1e-10, radii[i] - excess * w_i)\n                        radii[j] = max(1e-10, radii[j] - excess * w_j)\n                        changed = True\n        if not changed:\n            break\n    \n    # Final pass with proportional scaling to ensure all constraints satisfied\n    for _ in range(500):\n        changed = False\n        for i in range(n):\n            for j in range(i + 1, n):\n                dist = np.linalg.norm(centers[i] - centers[j])\n                if radii[i] + radii[j] > dist + 1e-10:\n                    total = radii[i] + radii[j]\n                    if total > 1e-10:\n                        radii[i] = radii[i] * dist / total\n                        radii[j] = radii[j] * dist / total\n                        changed = True\n        if not changed:\n            break\n    \n    return radii\n\n\n# EVOLVE-BLOCK-END\n\n\n# This part remains fixed (not evolved)\ndef run_packing():\n    \"\"\"Run the circle packing constructor for n=26\"\"\"\n    centers, radii, sum_radii = construct_packing()\n    return centers, radii, sum_radii\n\n\ndef visualize(centers, radii):\n    \"\"\"\n    Visualize the circle packing\n\n    Args:\n        centers: np.array of shape (n, 2) with (x, y) coordinates\n        radii: np.array of shape (n) with radius of each circle\n    \"\"\"\n    import matplotlib.pyplot as plt\n    from matplotlib.patches import Circle\n\n    fig, ax = plt.subplots(figsize=(8, 8))\n\n    # Draw unit square\n    ax.set_xlim(0, 1)\n    ax.set_ylim(0, 1)\n    ax.set_aspect(\"equal\")\n    ax.grid(True)\n\n    # Draw circles\n    for i, (center, radius) in enumerate(zip(centers, radii)):\n        circle = Circle(center, radius, alpha=0.5)\n        ax.add_patch(circle)\n        ax.text(center[0], center[1], str(i), ha=\"center\", va=\"center\")\n\n    plt.title(f\"Circle Packing (n={len(centers)}, sum={sum(radii):.6f})\")\n    plt.show()\n\n\nif __name__ == \"__main__\":\n    centers, radii, sum_radii = run_packing()\n    print(f\"Sum of radii: {sum_radii}\")\n    # AlphaEvolve improved this to 2.635\n\n    # Uncomment to visualize:\n    visualize(centers, radii)\n\n```\n\n\n# Task\nSuggest improvements to the program that will improve its COMBINED_SCORE.\nThe system maintains diversity across these dimensions: score, complexity.\nDifferent solutions with similar combined_score but different features are valuable.\n\nYou MUST use the exact SEARCH/REPLACE diff format shown below to indicate changes:\n\n<<<<<<< SEARCH\n# Original code to find and replace (must match exactly)\n=======\n# New replacement code\n>>>>>>> REPLACE\n\nExample of valid diff format:\n<<<<<<< SEARCH\nfor i in range(m):\n    for j in range(p):\n        for k in range(n):\n            C[i, j] += A[i, k] * B[k, j]\n=======\n# Reorder loops for better memory access pattern\nfor i in range(m):\n    for k in range(n):\n        for j in range(p):\n            C[i, j] += A[i, k] * B[k, j]\n>>>>>>> REPLACE\n\n**CRITICAL**: You can suggest multiple changes. Each SEARCH section must EXACTLY match code in \"# Current Solution\" - copy it character-for-character, preserving all whitespace and indentation. Do NOT paraphrase or reformat.\nBe thoughtful about your changes and explain your reasoning thoroughly.\nInclude a concise docstring at the start of functions describing the exact approach taken.\n\nIMPORTANT: If an instruction header of \"## IMPORTANT: ...\" is given below the \"# Current Solution\", you MUST follow it. Otherwise, \nfocus on targeted improvements of the program. \n\n- Time limit: Programs should complete execution within 360 seconds; otherwise, they will timeout.", "responses": ["Looking at the current solution, I can see the problem: the circle positions are poorly chosen. The best solution (Program 2) achieves sum_radii=1.8309, but the current solution only gets 1.2181. The issue is that some circles are placed too close to edges (x=0.02, 0.98) which severely limits their radii.\n\nKey insights for improvement:\n1. Corner circles should be placed at optimal diagonal positions (\u22480.08-0.10 from both walls)\n2. Interior circles should use proper hexagonal spacing\n3. The 4-6-6-6-4 pattern needs better vertical spacing\n\nLet me create an optimized layout:\n\n<<<<<<< SEARCH\ndef construct_packing():\n    \"\"\"\n    Hexagonal packing for 26 circles in 4-6-6-6-4 row pattern.\n    Rows with 4 circles are offset inward, placed near walls.\n    Rows with 6 circles use hexagonal offset for dense packing.\n    Circles positioned close to walls maximize radii via wall constraints.\n    \n    Returns:\n        Tuple of (centers, radii, sum_of_radii)\n    \"\"\"\n    n = 26\n    centers = np.zeros((n, 2))\n    idx = 0\n    \n    # Row 1 (bottom): 4 circles near bottom wall\n    for x in [0.12, 0.38, 0.62, 0.88]:\n        centers[idx] = [x, 0.10]\n        idx += 1\n    \n    # Row 2: 6 circles with hexagonal offset (shifted right)\n    for x in [0.08, 0.26, 0.44, 0.62, 0.80, 0.98]:\n        centers[idx] = [x, 0.32]\n        idx += 1\n    \n    # Row 3: 6 circles aligned with row 1\n    for x in [0.02, 0.20, 0.38, 0.56, 0.74, 0.92]:\n        centers[idx] = [x, 0.54]\n        idx += 1\n    \n    # Row 4: 6 circles with hexagonal offset\n    for x in [0.08, 0.26, 0.44, 0.62, 0.80, 0.98]:\n        centers[idx] = [x, 0.76]\n        idx += 1\n    \n    # Row 5 (top): 4 circles near top wall\n    for x in [0.12, 0.38, 0.62, 0.88]:\n        centers[idx] = [x, 0.90]\n        idx += 1\n    \n    radii = compute_max_radii(centers)\n    return centers, radii, np.sum(radii)\n=======\ndef construct_packing():\n    \"\"\"\n    Optimized 4-6-6-6-4 hexagonal packing for 26 circles.\n    Corner circles placed at optimal diagonal distance (~0.08) from both walls.\n    Interior circles use proper hexagonal spacing with row offset.\n    Vertical spacing of ~0.18 between rows for optimal packing.\n    \n    Returns:\n        Tuple of (centers, radii, sum_of_radii)\n    \"\"\"\n    n = 26\n    centers = np.zeros((n, 2))\n    idx = 0\n    \n    # Row 1 (bottom): 4 circles - corners at optimal diagonal position\n    for x in [0.08, 0.36, 0.64, 0.92]:\n        centers[idx] = [x, 0.08]\n        idx += 1\n    \n    # Row 2: 6 circles with hexagonal offset\n    for x in [0.08, 0.24, 0.40, 0.56, 0.72, 0.92]:\n        centers[idx] = [x, 0.26]\n        idx += 1\n    \n    # Row 3: 6 circles aligned with row 1\n    for x in [0.16, 0.32, 0.48, 0.64, 0.80, 0.92]:\n        centers[idx] = [x, 0.44]\n        idx += 1\n    \n    # Row 4: 6 circles with hexagonal offset\n    for x in [0.08, 0.24, 0.40, 0.56, 0.72, 0.92]:\n        centers[idx] = [x, 0.62]\n        idx += 1\n    \n    # Row 5 (top): 4 circles - corners at optimal diagonal position\n    for x in [0.08, 0.36, 0.64, 0.92]:\n        centers[idx] = [x, 0.92]\n        idx += 1\n    \n    radii = compute_max_radii(centers)\n    return centers, radii, np.sum(radii)\n>>>>>>> REPLACE\n\n<<<<<<< SEARCH\ndef compute_max_radii(centers):\n    \"\"\"\n    Compute maximum valid radii using priority-based constraint resolution.\n    Circles closer to walls get priority (larger share) during overlap resolution\n    since they have less room to grow. Uses multiple passes for convergence.\n    \"\"\"\n    n = centers.shape[0]\n    radii = np.zeros(n)\n    \n    # Initialize with wall constraints\n    for i in range(n):\n        x, y = centers[i]\n        radii[i] = min(x, y, 1 - x, 1 - y)\n    \n    # Compute wall proximity (smaller = closer to wall = higher priority)\n    wall_dist = np.array([min(centers[i, 0], centers[i, 1], \n                             1 - centers[i, 0], 1 - centers[i, 1]) \n                          for i in range(n)])\n    \n    # Iteratively resolve circle-circle constraints with priority\n    for _ in range(1000):\n        changed = False\n        for i in range(n):\n            for j in range(i + 1, n):\n                dist = np.linalg.norm(centers[i] - centers[j])\n                if radii[i] + radii[j] > dist + 1e-10:\n                    total = radii[i] + radii[j]\n                    excess = total - dist\n                    if excess > 1e-10:\n                        # Weight reduction by inverse priority (further from wall = reduce more)\n                        w_i = wall_dist[i] / (wall_dist[i] + wall_dist[j] + 1e-10)\n                        w_j = wall_dist[j] / (wall_dist[i] + wall_dist[j] + 1e-10)\n                        radii[i] = max(1e-10, radii[i] - excess * w_i)\n                        radii[j] = max(1e-10, radii[j] - excess * w_j)\n                        changed = True\n        if not changed:\n            break\n    \n    # Final pass with proportional scaling to ensure all constraints satisfied\n    for _ in range(500):\n        changed = False\n        for i in range(n):\n            for j in range(i + 1, n):\n                dist = np.linalg.norm(centers[i] - centers[j])\n                if radii[i] + radii[j] > dist + 1e-10:\n                    total = radii[i] + radii[j]\n                    if total > 1e-10:\n                        radii[i] = radii[i] * dist / total\n                        radii[j] = radii[j] * dist / total\n                        changed = True\n        if not changed:\n            break\n    \n    return radii\n=======\ndef compute_max_radii(centers):\n    \"\"\"\n    Compute maximum valid radii using iterative proportional constraint resolution.\n    Each circle initialized with wall constraint, then circle-circle overlaps\n    resolved by proportional scaling to fairly distribute available space.\n    \"\"\"\n    n = centers.shape[0]\n    radii = np.zeros(n)\n    \n    # Initialize with wall constraints\n    for i in range(n):\n        x, y = centers[i]\n        radii[i] = min(x, y, 1 - x, 1 - y)\n    \n    # Iteratively resolve circle-circle constraints with proportional scaling\n    for _ in range(1000):\n        changed = False\n        for i in range(n):\n            for j in range(i + 1, n):\n                dist = np.linalg.norm(centers[i] - centers[j])\n                if radii[i] + radii[j] > dist + 1e-10:\n                    total = radii[i] + radii[j]\n                    if total > 1e-10:\n                        radii[i] = radii[i] * dist / total\n                        radii[j] = radii[j] * dist / total\n                        changed = True\n        if not changed:\n            break\n    \n    return radii\n>>>>>>> REPLACE"]}}, "generation": 0}